{
  "info": {
    "name": "Event Planner Auth API - COMPLETE",
    "description": "Complete API collection for Event Planner Auth Service with all essential routes",
    "version": "3.0.0",
    "schema": "https://schema.getpostman.com/json/collection/v2.1.0/collection.json"
  },
  "variable": [
    {
      "key": "baseUrl",
      "value": "http://localhost:3000",
      "type": "string"
    },
    {
      "key": "authToken",
      "value": "",
      "type": "string"
    },
    {
      "key": "userEmail",
      "value": "",
      "type": "string"
    },
    {
      "key": "otpCode",
      "value": "",
      "type": "string"
    },
    {
      "key": "personId",
      "value": "",
      "type": "string"
    },
    {
      "key": "googleIdToken",
      "value": "",
      "type": "string"
    },
    {
      "key": "appleIdentityToken",
      "value": "",
      "type": "string"
    }
  ],
  "auth": {
    "type": "bearer",
    "bearer": [
      {
        "key": "token",
        "value": "{{authToken}}",
        "type": "string"
      }
    ]
  },
  "item": [
    {
      "name": "🏠 Health & Status",
      "item": [
        {
          "name": "Health Check",
          "request": {
            "method": "GET",
            "header": [],
            "url": {
              "raw": "{{baseUrl}}/api/health",
              "host": ["{{baseUrl}}"],
              "path": ["api", "health"]
            },
            "description": "Basic health check (public)"
          },
          "response": []
        },
        {
          "name": "Health Detailed",
          "request": {
            "method": "GET",
            "header": [],
            "url": {
              "raw": "{{baseUrl}}/api/health/detailed",
              "host": ["{{baseUrl}}"],
              "path": ["api", "health", "detailed"]
            },
            "description": "Detailed health check (public)"
          },
          "response": []
        },
        {
          "name": "Root Info",
          "request": {
            "method": "GET",
            "header": [],
            "url": {
              "raw": "{{baseUrl}}/",
              "host": ["{{baseUrl}}"],
              "path": []
            },
            "description": "Root endpoint with service info"
          },
          "response": []
        }
      ]
    },
    {
      "name": "📝 Registration",
      "item": [
        {
          "name": "Check Email Availability",
          "request": {
            "method": "GET",
            "header": [],
            "url": {
              "raw": "{{baseUrl}}/api/auth/check-email/{{userEmail}}",
              "host": ["{{baseUrl}}"],
              "path": ["api", "auth", "check-email", "{{userEmail}}"]
            },
            "description": "Check if email is available for registration"
          },
          "response": []
        },
        {
          "name": "Check Username Availability",
          "request": {
            "method": "GET",
            "header": [],
            "url": {
              "raw": "{{baseUrl}}/api/auth/check-username/testuser",
              "host": ["{{baseUrl}}"],
              "path": ["api", "auth", "check-username", "testuser"]
            },
            "description": "Check if username is available for registration"
          },
          "response": []
        },
        {
          "name": "Register User",
          "request": {
            "method": "POST",
            "header": [
              {
                "key": "Content-Type",
                "value": "application/json"
              }
            ],
            "body": {
              "mode": "raw",
              "raw": "{\n  \"email\": \"{{userEmail}}\",\n  \"username\": \"testuser\",\n  \"password\": \"SecurePass123!\",\n  \"firstName\": \"John\",\n  \"lastName\": \"Doe\",\n  \"phone\": \"+33612345678\"\n}"
            },
            "url": {
              "raw": "{{baseUrl}}/api/auth/register",
              "host": ["{{baseUrl}}"],
              "path": ["api", "auth", "register"]
            },
            "description": "Register a new user account"
          },
          "response": []
        },
        {
          "name": "Verify Email with OTP",
          "request": {
            "method": "POST",
            "header": [
              {
                "key": "Content-Type",
                "value": "application/json"
              }
            ],
            "body": {
              "mode": "raw",
              "raw": "{\n  \"email\": \"{{userEmail}}\",\n  \"otpCode\": \"{{otpCode}}\"\n}"
            },
            "url": {
              "raw": "{{baseUrl}}/api/auth/verify-email",
              "host": ["{{baseUrl}}"],
              "path": ["api", "auth", "verify-email"]
            },
            "description": "Verify email address with OTP code"
          },
          "response": []
        },
        {
          "name": "Resend OTP",
          "request": {
            "method": "POST",
            "header": [
              {
                "key": "Content-Type",
                "value": "application/json"
              }
            ],
            "body": {
              "mode": "raw",
              "raw": "{\n  \"email\": \"{{userEmail}}\"\n}"
            },
            "url": {
              "raw": "{{baseUrl}}/api/auth/resend-otp",
              "host": ["{{baseUrl}}"],
              "path": ["api", "auth", "resend-otp"]
            },
            "description": "Resend OTP code for email verification"
          },
          "response": []
        }
      ]
    },
    {
      "name": "🔐 Authentication",
      "item": [
        {
          "name": "Login",
          "request": {
            "method": "POST",
            "header": [
              {
                "key": "Content-Type",
                "value": "application/json"
              }
            ],
            "body": {
              "mode": "raw",
              "raw": "{\n  \"email\": \"{{userEmail}}\",\n  \"password\": \"SecurePass123!\",\n  \"rememberMe\": false\n}"
            },
            "url": {
              "raw": "{{baseUrl}}/api/auth/login",
              "host": ["{{baseUrl}}"],
              "path": ["api", "auth", "login"]
            },
            "description": "Login with email and password"
          },
          "response": []
        },
        {
          "name": "Login with OTP",
          "request": {
            "method": "POST",
            "header": [
              {
                "key": "Content-Type",
                "value": "application/json"
              }
            ],
            "body": {
              "mode": "raw",
              "raw": "{\n  \"email\": \"{{userEmail}}\",\n  \"otpCode\": \"{{otpCode}}\"\n}"
            },
            "url": {
              "raw": "{{baseUrl}}/api/auth/login-otp",
              "host": ["{{baseUrl}}"],
              "path": ["api", "auth", "login-otp"]
            },
            "description": "Login with OTP code"
          },
          "response": []
        },
        {
          "name": "Refresh Token",
          "request": {
            "method": "POST",
            "header": [
              {
                "key": "Content-Type",
                "value": "application/json"
              }
            ],
            "body": {
              "mode": "raw",
              "raw": "{\n  \"refreshToken\": \"refresh_token_here\"\n}"
            },
            "url": {
              "raw": "{{baseUrl}}/api/auth/refresh-token",
              "host": ["{{baseUrl}}"],
              "path": ["api", "auth", "refresh-token"]
            },
            "description": "Refresh access token"
          },
          "response": []
        },
        {
          "name": "Validate Token",
          "request": {
            "method": "POST",
            "header": [
              {
                "key": "Content-Type",
                "value": "application/json"
              }
            ],
            "body": {
              "mode": "raw",
              "raw": "{\n  \"token\": \"{{authToken}}\"\n}"
            },
            "url": {
              "raw": "{{baseUrl}}/api/auth/validate-token",
              "host": ["{{baseUrl}}"],
              "path": ["api", "auth", "validate-token"]
            },
            "description": "Validate JWT token"
          },
          "response": []
        },
        {
          "name": "Logout",
          "request": {
            "method": "POST",
            "header": [],
            "url": {
              "raw": "{{baseUrl}}/api/auth/logout",
              "host": ["{{baseUrl}}"],
              "path": ["api", "auth", "logout"]
            },
            "description": "Logout user and invalidate tokens"
          },
          "response": []
        },
        {
          "name": "Get Profile",
          "request": {
            "method": "GET",
            "header": [],
            "url": {
              "raw": "{{baseUrl}}/api/auth/profile",
              "host": ["{{baseUrl}}"],
              "path": ["api", "auth", "profile"]
            },
            "description": "Get user profile"
          },
          "response": []
        },
        {
          "name": "Change Password",
          "request": {
            "method": "POST",
            "header": [
              {
                "key": "Content-Type",
                "value": "application/json"
              }
            ],
            "body": {
              "mode": "raw",
              "raw": "{\n  \"currentPassword\": \"SecurePass123!\",\n  \"newPassword\": \"NewSecurePass456!\"\n}"
            },
            "url": {
              "raw": "{{baseUrl}}/api/auth/change-password",
              "host": ["{{baseUrl}}"],
              "path": ["api", "auth", "change-password"]
            },
            "description": "Change user password"
          },
          "response": []
        }
      ]
    },
    {
      "name": "🔢 OTP Management",
      "item": [
        {
          "name": "Generate Email OTP",
          "request": {
            "method": "POST",
            "header": [
              {
                "key": "Content-Type",
                "value": "application/json"
              }
            ],
            "body": {
              "mode": "raw",
              "raw": "{\n  \"email\": \"{{userEmail}}\",\n  \"purpose\": \"login\"\n}"
            },
            "url": {
              "raw": "{{baseUrl}}/api/auth/otp/email/generate",
              "host": ["{{baseUrl}}"],
              "path": ["api", "auth", "otp", "email", "generate"]
            },
            "description": "Generate OTP for email"
          },
          "response": []
        },
        {
          "name": "Verify Email OTP",
          "request": {
            "method": "POST",
            "header": [
              {
                "key": "Content-Type",
                "value": "application/json"
              }
            ],
            "body": {
              "mode": "raw",
              "raw": "{\n  \"email\": \"{{userEmail}}\",\n  \"otpCode\": \"{{otpCode}}\"\n}"
            },
            "url": {
              "raw": "{{baseUrl}}/api/auth/otp/email/verify",
              "host": ["{{baseUrl}}"],
              "path": ["api", "auth", "otp", "email", "verify"]
            },
            "description": "Verify email OTP"
          },
          "response": []
        },
        {
          "name": "Forgot Password",
          "request": {
            "method": "POST",
            "header": [
              {
                "key": "Content-Type",
                "value": "application/json"
              }
            ],
            "body": {
              "mode": "raw",
              "raw": "{\n  \"email\": \"{{userEmail}}\"\n}"
            },
            "url": {
              "raw": "{{baseUrl}}/api/auth/forgot-password",
              "host": ["{{baseUrl}}"],
              "path": ["api", "auth", "forgot-password"]
            },
            "description": "Forgot password - send reset OTP"
          },
          "response": []
        },
        {
          "name": "Reset Password",
          "request": {
            "method": "POST",
            "header": [
              {
                "key": "Content-Type",
                "value": "application/json"
              }
            ],
            "body": {
              "mode": "raw",
              "raw": "{\n  \"email\": \"{{userEmail}}\",\n  \"otpCode\": \"{{otpCode}}\",\n  \"newPassword\": \"NewSecurePass456!\"\n}"
            },
            "url": {
              "raw": "{{baseUrl}}/api/auth/reset-password",
              "host": ["{{baseUrl}}"],
              "path": ["api", "auth", "reset-password"]
            },
            "description": "Reset password with OTP"
          },
          "response": []
        }
      ]
    },
    {
      "name": "🌐 OAuth Integration",
      "item": [
        {
          "name": "Google Sign-In",
          "request": {
            "method": "POST",
            "header": [
              {
                "key": "Content-Type",
                "value": "application/json"
              }
            ],
            "body": {
              "mode": "raw",
              "raw": "{\n  \"idToken\": \"{{googleIdToken}}\"\n}"
            },
            "url": {
              "raw": "{{baseUrl}}/api/oauth/google",
              "host": ["{{baseUrl}}"],
              "path": ["api", "oauth", "google"]
            },
            "description": "Authenticate with Google Sign-In"
          },
          "response": []
        },
        {
          "name": "Apple Sign-In",
          "request": {
            "method": "POST",
            "header": [
              {
                "key": "Content-Type",
                "value": "application/json"
              }
            ],
            "body": {
              "mode": "raw",
              "raw": "{\n  \"identityToken\": \"{{appleIdentityToken}}\"\n}"
            },
            "url": {
              "raw": "{{baseUrl}}/api/oauth/apple",
              "host": ["{{baseUrl}}"],
              "path": ["api", "oauth", "apple"]
            },
            "description": "Authenticate with Apple Sign-In"
          },
          "response": []
        }
      ]
    },
    {
      "name": "👥 User Management",
      "item": [
        {
          "name": "Get Users",
          "request": {
            "method": "GET",
            "header": [],
            "url": {
              "raw": "{{baseUrl}}/api/users?page=1&limit=20",
              "host": ["{{baseUrl}}"],
              "path": ["api", "users"],
              "query": [
                {
                  "key": "page",
                  "value": "1",
                  "description": "Page number"
                },
                {
                  "key": "limit",
                  "value": "20",
                  "description": "Items per page"
                }
              ]
            },
            "description": "Get users list with pagination"
          },
          "response": []
        },
        {
          "name": "Get User by ID",
          "request": {
            "method": "GET",
            "header": [],
            "url": {
              "raw": "{{baseUrl}}/api/users/{{personId}}",
              "host": ["{{baseUrl}}"],
              "path": ["api", "users", "{{personId}}"]
            },
            "description": "Get user details by ID"
          },
          "response": []
        },
        {
          "name": "Update User",
          "request": {
            "method": "PUT",
            "header": [
              {
                "key": "Content-Type",
                "value": "application/json"
              }
            ],
            "body": {
              "mode": "raw",
              "raw": "{\n  \"firstName\": \"John Updated\",\n  \"lastName\": \"Doe Updated\",\n  \"phone\": \"+33698765432\"\n}"
            },
            "url": {
              "raw": "{{baseUrl}}/api/users/{{personId}}",
              "host": ["{{baseUrl}}"],
              "path": ["api", "users", "{{personId}}"]
            },
            "description": "Update user details"
          },
          "response": []
        }
      ]
    },
    {
      "name": "🔑 Role Management",
      "item": [
        {
          "name": "Get Roles",
          "request": {
            "method": "GET",
            "header": [],
            "url": {
              "raw": "{{baseUrl}}/api/roles?page=1&limit=20",
              "host": ["{{baseUrl}}"],
              "path": ["api", "roles"],
              "query": [
                {
                  "key": "page",
                  "value": "1",
                  "description": "Page number"
                },
                {
                  "key": "limit",
                  "value": "20",
                  "description": "Items per page"
                }
              ]
            },
            "description": "Get roles list with pagination"
          },
          "response": []
        },
        {
          "name": "Create Role",
          "request": {
            "method": "POST",
            "header": [
              {
                "key": "Content-Type",
                "value": "application/json"
              }
            ],
            "body": {
              "mode": "raw",
              "raw": "{\n  \"name\": \"Event Manager\",\n  \"description\": \"Can manage events and tickets\",\n  \"permissions\": [\"events.create\", \"events.update\", \"tickets.read\"]\n}"
            },
            "url": {
              "raw": "{{baseUrl}}/api/roles",
              "host": ["{{baseUrl}}"],
              "path": ["api", "roles"]
            },
            "description": "Create a new role"
          },
          "response": []
        }
      ]
    },
    {
      "name": "🛡️ Permission Management",
      "item": [
        {
          "name": "Get Permissions",
          "request": {
            "method": "GET",
            "header": [],
            "url": {
              "raw": "{{baseUrl}}/api/permissions?page=1&limit=20",
              "host": ["{{baseUrl}}"],
              "path": ["api", "permissions"],
              "query": [
                {
                  "key": "page",
                  "value": "1",
                  "description": "Page number"
                },
                {
                  "key": "limit",
                  "value": "20",
                  "description": "Items per page"
                }
              ]
            },
            "description": "Get permissions list with pagination"
          },
          "response": []
        },
        {
          "name": "Check User Permission",
          "request": {
            "method": "GET",
            "header": [],
            "url": {
              "raw": "{{baseUrl}}/api/permissions/user/{{personId}}/check/events.create",
              "host": ["{{baseUrl}}"],
              "path": ["api", "permissions", "user", "{{personId}}", "check", "events.create"]
            },
            "description": "Check if user has specific permission"
          },
          "response": []
        }
      ]
    },
    {
      "name": "📊 Dashboard & Metrics",
      "item": [
        {
          "name": "Dashboard Data",
          "request": {
            "method": "GET",
            "header": [],
            "url": {
              "raw": "{{baseUrl}}/api/dashboard",
              "host": ["{{baseUrl}}"],
              "path": ["api", "dashboard"]
            },
            "description": "Get dashboard data (requires admin.dashboard.read permission)"
          },
          "response": []
        },
        {
          "name": "Metrics",
          "request": {
            "method": "GET",
            "header": [],
            "url": {
              "raw": "{{baseUrl}}/api/metrics",
              "host": ["{{baseUrl}}"],
              "path": ["api", "metrics"]
            },
            "description": "Get service metrics (public for monitoring)"
          },
          "response": []
        }
      ]
    }
  ],
  "event": [
    {
      "listen": "prerequest",
      "script": {
        "exec": [
          "// Auto-refresh token if expired",
          "if (pm.collectionVariables.get('authToken') === '') {",
          "    pm.collectionVariables.set('authToken', 'your_real_jwt_token');",
          "}"
        ],
        "type": "text/javascript"
      }
    }
  ]
}
